odrive_can/__init__.py
odrive_can/can_utils.py
odrive_can/cli.py
odrive_can/enums.py
odrive_can/inspector.py
odrive_can/interface.py
odrive_can/linear_model.py
odrive_can/mock.py
odrive_can/odrive.py
odrive_can/py.typed
odrive_can/setpoints.py
odrive_can/timer.py
odrive_can/tools.py
odrive_can/utils.py
odrive_can/dbc/odrive-cansimple-0.5.6.dbc
odrive_can/dbc/odrive-cansimple-0.6.10.dbc
odrive_can/examples/__init__.py
odrive_can/examples/position_control.py
odrive_can/examples/velocity_control.py
odrive_can/examples/watchdog.py
odrive_can-2.1.0.dist-info/LICENCE
odrive_can-2.1.0.dist-info/METADATA
odrive_can-2.1.0.dist-info/WHEEL
odrive_can-2.1.0.dist-info/entry_points.txt
odrive_can-2.1.0.dist-info/top_level.txt
odrive_can-2.1.0.dist-info/RECORD
