Metadata-Version: 2.2
Name: odrive-can
Version: 2.1.0
Summary: Command ODrive over CAN with a simple interface
Author-email: ROX Automation <dev@roxautomation.com>
License: MIT
Project-URL: Homepage, https://gitlab.com/roxautomation/components/odrive-can
Classifier: Development Status :: 4 - Beta
Classifier: Intended Audience :: Developers
Classifier: Operating System :: OS Independent
Classifier: Programming Language :: Python
Classifier: Programming Language :: Python :: 3.11
Classifier: Topic :: Software Development :: Libraries :: Python Modules
Classifier: Typing :: Typed
Requires-Python: >=3.11
License-File: LICENCE
Requires-Dist: click
Requires-Dist: cantools
Requires-Dist: python-can
Requires-Dist: coloredlogs
Provides-Extra: dev
Requires-Dist: invoke; extra == "dev"
Requires-Dist: ipython; extra == "dev"
Requires-Dist: mypy; extra == "dev"
Requires-Dist: odrive==0.6.8; extra == "dev"
Requires-Dist: pre-commit; extra == "dev"
Requires-Dist: pytest; extra == "dev"
Requires-Dist: pytest-asyncio; extra == "dev"
Requires-Dist: pytest-cov; extra == "dev"
Requires-Dist: ruff; extra == "dev"
Provides-Extra: ci
Requires-Dist: pytest-mock; extra == "ci"
